colbert_rag/__init__.py
colbert_rag/config.py
colbert_rag/data/__init__.py
colbert_rag/data/git_repo.py
colbert_rag/indexer/__init__.py
colbert_rag/indexer/base.py
colbert_rag/indexer/git_repo.py
colbert_rag/models.py
colbert_rag/proto/__init__.py
colbert_rag/proto/colbertrag_pb2.py
colbert_rag/proto/colbertrag_pb2.pyi
colbert_rag/proto/colbertrag_pb2_grpc.py
colbert_rag/proto/wrapper.py
colbert_rag/server/__init__.py
colbert_rag/server/base.py
colbert_rag/server/fastapi.py
colbert_rag/server/grpc.py
colbert_rag-0.1.2.dist-info/LICENSE
colbert_rag-0.1.2.dist-info/METADATA
colbert_rag-0.1.2.dist-info/WHEEL
colbert_rag-0.1.2.dist-info/entry_points.txt
colbert_rag-0.1.2.dist-info/RECORD
