Metadata-Version: 2.1
Name: colbert-rag
Version: 0.1.2
Summary: RAG using Langchain and RAGatouille
Author: ricardo-larosa
Author-email: ricardo@larosa.dev
Requires-Python: >=3.10,<4.0
Classifier: Programming Language :: Python :: 3
Classifier: Programming Language :: Python :: 3.10
Classifier: Programming Language :: Python :: 3.11
Classifier: Programming Language :: Python :: 3.12
Requires-Dist: RAGatouille (>=0.0.8.post2,<0.0.9)
Requires-Dist: fastapi (>=0.112.0,<0.113.0)
Requires-Dist: gitpython (>=3.1.43,<4.0.0)
Requires-Dist: grpcio-tools (>=1.65.1,<2.0.0)
Requires-Dist: langchain-openai (==0.1.7)
Requires-Dist: pygments (>=2.18.0,<3.0.0)
Requires-Dist: python-dotenv (>=1.0.1,<2.0.0)
Requires-Dist: uvicorn (>=0.30.6,<0.31.0)
